detection/__init__.py
detection/detector.py
detection/detectors/__init__.py
detection/detectors/blob/__init__.py
detection/detectors/blob/detector.py
detection/detectors/simple/__init__.py
detection/detectors/simple/detector.py
detection/helpers.py
detection/maker.py
detection/py.typed
detection-0.1.2.dist-info/LICENSE.txt
detection-0.1.2.dist-info/WHEEL
detection-0.1.2.dist-info/METADATA
detection-0.1.2.dist-info/RECORD
