Metadata-Version: 2.1
Name: detection
Version: 0.1.2
Summary: A motion detector
Home-page: https://gitlab.com/kahara/python-detection
License: MIT
Author: Joni Kähärä
Author-email: joni.kahara@async.fi
Requires-Python: >=3.7,<4.0
Classifier: License :: OSI Approved :: MIT License
Classifier: Programming Language :: Python :: 3
Classifier: Programming Language :: Python :: 3.7
Classifier: Programming Language :: Python :: 3.8
Requires-Dist: opencv-contrib-python-headless (>=4.2.0,<5.0.0)
Requires-Dist: scenegen (==0.1.2)
